.DS_Store
alphad3m/.DS_Store
alphad3m/__init__.py
alphad3m/api.py
alphad3m/automl.py
alphad3m/grammar_loader.py
alphad3m/main.py
alphad3m/multiprocessing.py
alphad3m/primitive_loader.py
alphad3m/utils.py
alphad3m/data_ingestion/__init__.py
alphad3m/data_ingestion/data_profiler.py
alphad3m/grpc_api/__init__.py
alphad3m/grpc_api/grpc_client.py
alphad3m/grpc_api/grpc_logger.py
alphad3m/grpc_api/grpc_server.py
alphad3m/hyperparameter_tuning/__init__.py
alphad3m/hyperparameter_tuning/bayesian.py
alphad3m/hyperparameter_tuning/primitive_config.py
alphad3m/metafeature/__init__.py
alphad3m/metafeature/metafeature_extractor.py
alphad3m/metalearning/__init__.py
alphad3m/metalearning/dataset_profiler.py
alphad3m/metalearning/dataset_similarity.py
alphad3m/metalearning/grammar_builder.py
alphad3m/metalearning/nnet_trainer.py
alphad3m/metalearning/resource_builder.py
alphad3m/pipeline_operations/__init__.py
alphad3m/pipeline_operations/pipeline_execute.py
alphad3m/pipeline_operations/pipeline_score.py
alphad3m/pipeline_operations/pipeline_test.py
alphad3m/pipeline_operations/pipeline_train.py
alphad3m/pipeline_operations/pipeline_tune.py
alphad3m/pipeline_search/Arena.py
alphad3m/pipeline_search/Coach.py
alphad3m/pipeline_search/Game.py
alphad3m/pipeline_search/MCTS.py
alphad3m/pipeline_search/NeuralNet.py
alphad3m/pipeline_search/__init__.py
alphad3m/pipeline_search/utils.py
alphad3m/pipeline_search/pipeline/NNet.py
alphad3m/pipeline_search/pipeline/PipelineGame.py
alphad3m/pipeline_search/pipeline/PipelineLogic.py
alphad3m/pipeline_search/pipeline/PipelineNNet.py
alphad3m/pipeline_search/pipeline/PipelinePlayers.py
alphad3m/pipeline_search/pipeline/__init__.py
alphad3m/pipeline_synthesis/__init__.py
alphad3m/pipeline_synthesis/d3mpipeline_builder.py
alphad3m/pipeline_synthesis/setup_search.py
alphad3m/pipeline_synthesis/templates.py
alphad3m/resource/base_grammar.bnf
alphad3m/resource/base_grammar_old.bnf
alphad3m/resource/hyperparams.json
alphad3m-0.24.0.dist-info/LICENSE.txt
alphad3m-0.24.0.dist-info/METADATA
alphad3m-0.24.0.dist-info/NOTICE.txt
alphad3m-0.24.0.dist-info/WHEEL
alphad3m-0.24.0.dist-info/entry_points.txt
alphad3m-0.24.0.dist-info/top_level.txt
alphad3m-0.24.0.dist-info/RECORD
