Metadata-Version: 2.1
Name: alphad3m
Version: 0.24.0
Summary: AlphaD3M: NYU's AutoML System
Home-page: https://gitlab.com/ViDA-NYU/d3m/alphad3m
Author: Remi Rampin, Roque Lopez, Raoni Lourenco
Author-email: remi.rampin@nyu.edu, rlopez@nyu.edu, raoni@nyu.edu
Maintainer: Remi Rampin, Roque Lopez
Maintainer-email: remi.rampin@nyu.edu, rlopez@nyu.edu
License: Apache-2.0
Keywords: datadrivendiscovery,automl,d3m,ta2,nyu
Platform: UNKNOWN
Classifier: Development Status :: 5 - Production/Stable
Classifier: Intended Audience :: Science/Research
Classifier: License :: OSI Approved :: Apache Software License
Classifier: Topic :: Scientific/Engineering
License-File: LICENSE.txt
License-File: NOTICE.txt
Requires-Dist: Cython
Requires-Dist: SQLAlchemy (<1.4,>=1.2)
Requires-Dist: datamart-profiler (<0.10,>=0.9)
Requires-Dist: nltk
Requires-Dist: numpy
Requires-Dist: scipy
Requires-Dist: smac (<0.14,>=0.13)
Requires-Dist: ConfigSpace (<0.5,>=0.4.19)
Requires-Dist: scikit-learn (==0.22.2.post1)
Requires-Dist: torch (>=1.7)
Requires-Dist: PyYAML
Requires-Dist: metalearn (==0.6.2)
Requires-Dist: d3m
Requires-Dist: d3m-automl-rpc
Requires-Dist: d3m-interface
